yfinance_fetch/__init__.py
yfinance_fetch/example_usage.py
yfinance_fetch/yfinance_fetch.py
yfinance_fetch-0.0.3.dist-info/licenses/LICENSE.txt
yfinance_fetch-0.0.3.dist-info/METADATA
yfinance_fetch-0.0.3.dist-info/WHEEL
yfinance_fetch-0.0.3.dist-info/top_level.txt
yfinance_fetch-0.0.3.dist-info/RECORD
